[
  {
    "delegator": "misterdelegation",
    "sp": 1012073.0507956817,
    "time": "2018-06-01 17:45:06",
    "vests": 2033154493.32
  },
  {
    "delegator": "byubat",
    "sp": 201812.36813429318,
    "time": "2018-11-27 06:23:15",
    "vests": 405421054.1
  },
  {
    "delegator": "freedom",
    "sp": 149335.38805647328,
    "time": "2018-05-30 19:30:12",
    "vests": 300000000
  },
  {
    "delegator": "jaewoocho",
    "sp": 49778.46268549109,
    "time": "2018-12-05 08:53:21",
    "vests": 100000000
  },
  {
    "delegator": "tombstone",
    "sp": 25315.059041403296,
    "time": "2018-05-22 16:54:18",
    "vests": 50855445.66
  },
  {
    "delegator": "arama",
    "sp": 21664.194178324946,
    "time": "2018-05-27 14:11:45",
    "vests": 43521219.84
  },
  {
    "delegator": "goodnewworld",
    "sp": 20025.05841993024,
    "time": "2018-12-19 13:45:03",
    "vests": 40228358.49
  },
  {
    "delegator": "i-d",
    "sp": 15187.81495350715,
    "time": "2018-05-24 05:56:36",
    "vests": 30510815.59
  },
  {
    "delegator": "cool191",
    "sp": 13147.124390783847,
    "time": "2018-12-29 14:49:12",
    "vests": 26411270.42
  },
  {
    "delegator": "bramd",
    "sp": 10144.19593429415,
    "time": "2018-04-18 04:21:18",
    "vests": 20378684.65
  },
  {
    "delegator": "thomasmore",
    "sp": 10125.965941243314,
    "time": "2018-05-22 19:31:48",
    "vests": 20342062.4
  },
  {
    "delegator": "kwonjs77",
    "sp": 10118.174740709937,
    "time": "2018-06-06 13:40:03",
    "vests": 20326410.65
  },
  {
    "delegator": "jobviet",
    "sp": 7602.961210924966,
    "time": "2019-01-04 02:18:18",
    "vests": 15273595.85
  },
  {
    "delegator": "steemtopark",
    "sp": 7115.720832260715,
    "time": "2018-06-26 13:22:06",
    "vests": 14294778.2
  },
  {
    "delegator": "tradingideas",
    "sp": 7088.077249064964,
    "time": "2018-05-23 01:57:39",
    "vests": 14239244.98
  },
  {
    "delegator": "orientaledu",
    "sp": 6063.9298165446235,
    "time": "2018-06-28 10:24:54",
    "vests": 12181834.25
  },
  {
    "delegator": "roelandp",
    "sp": 5063.0819650504,
    "time": "2018-05-22 10:31:09",
    "vests": 10171230.07
  },
  {
    "delegator": "heeyaa35",
    "sp": 5060.0897318799125,
    "time": "2018-06-02 18:43:45",
    "vests": 10165218.97
  },
  {
    "delegator": "lighthil",
    "sp": 5055.93645091221,
    "time": "2018-06-18 10:48:57",
    "vests": 10156875.44
  },
  {
    "delegator": "supergiant",
    "sp": 5013.070623782927,
    "time": "2018-11-25 04:33:00",
    "vests": 10070762.24
  },
  {
    "delegator": "absolutefive",
    "sp": 5004.022890405212,
    "time": "2018-12-27 15:25:51",
    "vests": 10052586.24
  },
  {
    "delegator": "forealife",
    "sp": 4016.480448648349,
    "time": "2018-10-28 12:10:33",
    "vests": 8068711.31
  },
  {
    "delegator": "nexgen",
    "sp": 3035.814249413627,
    "time": "2018-06-04 06:55:51",
    "vests": 6098650.07
  },
  {
    "delegator": "warjar",
    "sp": 3028.1217794831405,
    "time": "2018-07-22 17:31:06",
    "vests": 6083196.66
  },
  {
    "delegator": "forykw",
    "sp": 3012.421010209968,
    "time": "2018-10-28 03:04:48",
    "vests": 6051655.37
  },
  {
    "delegator": "nateaguila",
    "sp": 3010.1607842668095,
    "time": "2019-01-10 03:27:42",
    "vests": 6047114.8
  },
  {
    "delegator": "kevinwong",
    "sp": 2025.09586139842,
    "time": "2018-05-23 17:41:21",
    "vests": 4068216.96
  },
  {
    "delegator": "jsquare",
    "sp": 2007.269273009186,
    "time": "2018-11-06 12:30:00",
    "vests": 4032405.11
  },
  {
    "delegator": "koinbot",
    "sp": 2004.167124015243,
    "time": "2018-12-04 16:08:39",
    "vests": 4026173.2
  },
  {
    "delegator": "drorion",
    "sp": 1991.1385074196437,
    "time": "2018-12-10 07:21:39",
    "vests": 4000000
  },
  {
    "delegator": "ys1302",
    "sp": 1822.6407508170025,
    "time": "2018-05-23 03:54:15",
    "vests": 3661504.7
  },
  {
    "delegator": "beerbloke",
    "sp": 1721.3338934573894,
    "time": "2018-05-23 17:02:36",
    "vests": 3457989.26
  },
  {
    "delegator": "otage",
    "sp": 1590.431495022585,
    "time": "2019-01-06 05:16:48",
    "vests": 3195019.31
  },
  {
    "delegator": "zzings",
    "sp": 1534.0104399631077,
    "time": "2018-06-03 16:25:33",
    "vests": 3081675
  },
  {
    "delegator": "jewel-lover",
    "sp": 1518.9411702232558,
    "time": "2018-05-22 05:29:21",
    "vests": 3051402.33
  },
  {
    "delegator": "freegon",
    "sp": 1505.4423462691295,
    "time": "2018-11-06 15:24:03",
    "vests": 3024284.53
  },
  {
    "delegator": "michelios",
    "sp": 1503.7566732979797,
    "time": "2018-11-27 03:34:48",
    "vests": 3020898.18
  },
  {
    "delegator": "howtostartablog",
    "sp": 1244.4615671372774,
    "time": "2018-06-15 14:53:00",
    "vests": 2500000
  },
  {
    "delegator": "bitrocker2020",
    "sp": 1214.6813081427524,
    "time": "2018-05-29 16:35:33",
    "vests": 2440174.41
  },
  {
    "delegator": "dmoons.kim",
    "sp": 1214.2797452842685,
    "time": "2018-06-05 00:20:06",
    "vests": 2439367.71
  },
  {
    "delegator": "feelsogood",
    "sp": 1203.0615713765408,
    "time": "2018-11-26 07:24:54",
    "vests": 2416831.51
  },
  {
    "delegator": "jirka.marek",
    "sp": 1125.826239530985,
    "time": "2018-10-08 12:12:03",
    "vests": 2261673.38
  },
  {
    "delegator": "funworlding",
    "sp": 1113.0025807776474,
    "time": "2018-06-06 12:16:57",
    "vests": 2235911.92
  },
  {
    "delegator": "kingbit",
    "sp": 1022.6736266420718,
    "time": "2018-07-01 13:07:57",
    "vests": 2054450
  },
  {
    "delegator": "exyle.steemhunt",
    "sp": 1012.6223495009249,
    "time": "2018-05-22 07:48:24",
    "vests": 2034257.98
  },
  {
    "delegator": "mastertri",
    "sp": 1012.585055476681,
    "time": "2018-05-23 00:46:51",
    "vests": 2034183.06
  },
  {
    "delegator": "zet",
    "sp": 1012.1844135197567,
    "time": "2018-05-30 15:16:30",
    "vests": 2033378.21
  },
  {
    "delegator": "aromi",
    "sp": 1011.7832389332818,
    "time": "2018-06-07 05:11:09",
    "vests": 2032572.29
  },
  {
    "delegator": "kview",
    "sp": 1011.6608984055396,
    "time": "2018-06-09 12:39:54",
    "vests": 2032326.52
  },
  {
    "delegator": "glory7",
    "sp": 1011.6038821543797,
    "time": "2018-06-10 14:30:12",
    "vests": 2032211.98
  },
  {
    "delegator": "thegreatgatsby",
    "sp": 1011.3537204901537,
    "time": "2018-06-15 07:59:54",
    "vests": 2031709.43
  },
  {
    "delegator": "happyberrysboy",
    "sp": 1010.6915176010486,
    "time": "2018-06-27 18:07:09",
    "vests": 2030379.13
  },
  {
    "delegator": "helix",
    "sp": 1010.1435164610366,
    "time": "2018-07-08 08:09:36",
    "vests": 2029278.25
  },
  {
    "delegator": "futile",
    "sp": 1009.3681073920922,
    "time": "2018-07-22 20:07:45",
    "vests": 2027720.53
  },
  {
    "delegator": "olorin",
    "sp": 1008.0517806583758,
    "time": "2018-08-16 08:10:15",
    "vests": 2025076.16
  },
  {
    "delegator": "yangpankil27",
    "sp": 1004.8851088210995,
    "time": "2018-10-14 08:40:33",
    "vests": 2018714.63
  },
  {
    "delegator": "storysharing",
    "sp": 1004.7744562763959,
    "time": "2018-10-16 09:49:09",
    "vests": 2018492.34
  },
  {
    "delegator": "relaxkim",
    "sp": 1004.0167036281662,
    "time": "2018-10-30 10:15:09",
    "vests": 2016970.09
  },
  {
    "delegator": "discovereurovelo",
    "sp": 1002.9264706719673,
    "time": "2018-11-19 14:07:12",
    "vests": 2014779.92
  },
  {
    "delegator": "shellyduncan",
    "sp": 1002.842220623872,
    "time": "2018-11-21 02:59:03",
    "vests": 2014610.67
  },
  {
    "delegator": "gungunkrishu",
    "sp": 1000.6902976819782,
    "time": "2018-12-29 16:39:09",
    "vests": 2010287.67
  },
  {
    "delegator": "abcteacher",
    "sp": 1000.6541336288373,
    "time": "2018-12-30 08:12:36",
    "vests": 2010215.02
  },
  {
    "delegator": "legend36",
    "sp": 1000.6464677455839,
    "time": "2018-12-30 11:31:15",
    "vests": 2010199.62
  },
  {
    "delegator": "vimva",
    "sp": 1000.1340582063918,
    "time": "2019-01-08 16:23:03",
    "vests": 2009170.24
  },
  {
    "delegator": "r2cornell",
    "sp": 1000.1225344922801,
    "time": "2019-01-08 21:20:51",
    "vests": 2009147.09
  },
  {
    "delegator": "andyx",
    "sp": 802.9153382508656,
    "time": "2018-06-03 08:18:21",
    "vests": 1612977.37
  },
  {
    "delegator": "jasonshick",
    "sp": 755.2773793279282,
    "time": "2018-09-04 01:32:45",
    "vests": 1517277.43
  },
  {
    "delegator": "khimgoh",
    "sp": 707.861093855022,
    "time": "2018-06-17 15:33:57",
    "vests": 1422022.81
  },
  {
    "delegator": "eastmael",
    "sp": 700.0269842868107,
    "time": "2019-01-10 09:33:33",
    "vests": 1406284.86
  },
  {
    "delegator": "d-zero",
    "sp": 630.1549722429255,
    "time": "2019-01-06 16:10:42",
    "vests": 1265918.91
  },
  {
    "delegator": "karamyog",
    "sp": 601.049226351328,
    "time": "2018-12-10 15:50:27",
    "vests": 1207448.35
  },
  {
    "delegator": "stokjockey",
    "sp": 600.0137596597756,
    "time": "2019-01-10 16:17:12",
    "vests": 1205368.2
  },
  {
    "delegator": "lotusofmymom",
    "sp": 506.12611833758285,
    "time": "2018-05-29 08:30:03",
    "vests": 1016757.23
  },
  {
    "delegator": "heonbros",
    "sp": 506.0053557871079,
    "time": "2018-06-02 22:00:33",
    "vests": 1016514.63
  },
  {
    "delegator": "teoit",
    "sp": 505.98720655961273,
    "time": "2018-06-03 14:27:39",
    "vests": 1016478.17
  },
  {
    "delegator": "pandafam",
    "sp": 505.9661452920505,
    "time": "2018-06-04 09:33:57",
    "vests": 1016435.86
  },
  {
    "delegator": "remnant39",
    "sp": 505.9356460279631,
    "time": "2018-06-05 13:15:30",
    "vests": 1016374.59
  },
  {
    "delegator": "dragonticketer",
    "sp": 505.8962463747475,
    "time": "2018-06-07 00:59:27",
    "vests": 1016295.44
  },
  {
    "delegator": "kibumh",
    "sp": 505.88319943967764,
    "time": "2018-06-07 12:49:36",
    "vests": 1016269.23
  },
  {
    "delegator": "kgbinternational",
    "sp": 505.79769995216907,
    "time": "2018-06-10 18:20:36",
    "vests": 1016097.47
  },
  {
    "delegator": "jeffjagoe",
    "sp": 505.4822189892072,
    "time": "2018-06-22 15:28:21",
    "vests": 1015463.7
  },
  {
    "delegator": "yunoyang",
    "sp": 505.20186170951627,
    "time": "2018-07-03 10:13:51",
    "vests": 1014900.49
  },
  {
    "delegator": "itshim",
    "sp": 503.98685903659634,
    "time": "2018-08-17 18:30:00",
    "vests": 1012459.67
  },
  {
    "delegator": "toocurious",
    "sp": 503.9261741127364,
    "time": "2018-08-19 23:59:42",
    "vests": 1012337.76
  },
  {
    "delegator": "freedomno1",
    "sp": 503.5928425930556,
    "time": "2018-09-01 06:53:03",
    "vests": 1011668.13
  },
  {
    "delegator": "gwoo",
    "sp": 503.43319808537694,
    "time": "2018-09-07 05:40:12",
    "vests": 1011347.42
  },
  {
    "delegator": "jznsamuel",
    "sp": 501.26975640721776,
    "time": "2018-11-26 12:27:51",
    "vests": 1007001.28
  },
  {
    "delegator": "iansart",
    "sp": 500.53537474721867,
    "time": "2018-12-22 20:31:45",
    "vests": 1005525.98
  },
  {
    "delegator": "ocupation",
    "sp": 500.31363658518615,
    "time": "2018-12-30 19:48:12",
    "vests": 1005080.53
  },
  {
    "delegator": "epitt925",
    "sp": 500.22094410981947,
    "time": "2019-01-03 03:48:30",
    "vests": 1004894.32
  },
  {
    "delegator": "pearlumie",
    "sp": 500.2027451038616,
    "time": "2019-01-03 19:29:12",
    "vests": 1004857.76
  },
  {
    "delegator": "changyoon",
    "sp": 500.1040642794339,
    "time": "2019-01-07 08:28:15",
    "vests": 1004659.52
  },
  {
    "delegator": "topping",
    "sp": 500.1040543237414,
    "time": "2019-01-07 08:28:45",
    "vests": 1004659.5
  },
  {
    "delegator": "armdown",
    "sp": 405.0284848344832,
    "time": "2018-05-24 08:29:33",
    "vests": 813662.1
  },
  {
    "delegator": "superoo7",
    "sp": 402.74109976208337,
    "time": "2018-09-09 07:14:21",
    "vests": 809066.97
  },
  {
    "delegator": "yoon",
    "sp": 305.77941436597945,
    "time": "2018-05-23 12:58:03",
    "vests": 614280.55
  },
  {
    "delegator": "kungdel",
    "sp": 303.7681354925573,
    "time": "2018-05-23 11:59:30",
    "vests": 610240.09
  },
  {
    "delegator": "dreamien",
    "sp": 303.7653030980305,
    "time": "2018-05-23 16:17:24",
    "vests": 610234.4
  },
  {
    "delegator": "japanguide",
    "sp": 303.6972957623096,
    "time": "2018-05-27 23:46:09",
    "vests": 610097.78
  },
  {
    "delegator": "boostyou",
    "sp": 303.6066043811428,
    "time": "2018-06-02 16:53:09",
    "vests": 609915.59
  },
  {
    "delegator": "zorba",
    "sp": 303.5294477639803,
    "time": "2018-06-07 13:32:24",
    "vests": 609760.59
  },
  {
    "delegator": "josalarcon2",
    "sp": 300.38707777218707,
    "time": "2018-12-18 21:35:15",
    "vests": 603447.88
  },
  {
    "delegator": "ideas-abstractas",
    "sp": 300.3719948979934,
    "time": "2018-12-19 19:21:18",
    "vests": 603417.58
  },
  {
    "delegator": "anomalogy",
    "sp": 280.3336846996414,
    "time": "2018-12-20 16:12:18",
    "vests": 563162.6
  },
  {
    "delegator": "mcfarhat",
    "sp": 253.1402481419547,
    "time": "2018-05-23 11:44:21",
    "vests": 508533.68
  },
  {
    "delegator": "felander",
    "sp": 253.12922221246987,
    "time": "2018-05-24 07:48:57",
    "vests": 508511.53
  },
  {
    "delegator": "maurice1975",
    "sp": 251.79264560013306,
    "time": "2018-09-01 13:37:03",
    "vests": 505826.48
  },
  {
    "delegator": "joannewong",
    "sp": 251.19549320606538,
    "time": "2018-10-16 06:20:51",
    "vests": 504626.86
  },
  {
    "delegator": "enisshkurti",
    "sp": 250.65891622323966,
    "time": "2018-11-24 19:20:45",
    "vests": 503548.93
  },
  {
    "delegator": "giovaabbatichio",
    "sp": 250.29824637185192,
    "time": "2018-12-20 15:39:51",
    "vests": 502824.38
  },
  {
    "delegator": "altrosa",
    "sp": 250.00497655894037,
    "time": "2019-01-10 17:35:36",
    "vests": 502235.23
  },
  {
    "delegator": "flash07",
    "sp": 226.15396963457982,
    "time": "2018-10-09 20:41:12",
    "vests": 454320.92
  },
  {
    "delegator": "ziscad",
    "sp": 202.51533754342069,
    "time": "2018-05-23 04:35:33",
    "vests": 406833.25
  },
  {
    "delegator": "romankibo",
    "sp": 202.5100460928372,
    "time": "2018-05-23 16:38:27",
    "vests": 406822.62
  },
  {
    "delegator": "deuksoo84",
    "sp": 202.50637244229102,
    "time": "2018-05-24 01:00:00",
    "vests": 406815.24
  },
  {
    "delegator": "thomas-bm",
    "sp": 202.49622759159573,
    "time": "2018-05-25 00:23:21",
    "vests": 406794.86
  },
  {
    "delegator": "revisesociology",
    "sp": 202.4782028102573,
    "time": "2018-05-26 17:24:33",
    "vests": 406758.65
  },
  {
    "delegator": "knight4sky",
    "sp": 202.3783322805714,
    "time": "2018-06-05 04:01:03",
    "vests": 406558.02
  },
  {
    "delegator": "rimowa",
    "sp": 202.2908068096315,
    "time": "2018-06-13 10:43:15",
    "vests": 406382.19
  },
  {
    "delegator": "yandot",
    "sp": 201.63373110218302,
    "time": "2018-08-14 04:35:06",
    "vests": 405062.19
  },
  {
    "delegator": "espoem",
    "sp": 201.5712342422814,
    "time": "2018-08-19 22:18:39",
    "vests": 404936.64
  },
  {
    "delegator": "jeaniepearl",
    "sp": 201.55382173603402,
    "time": "2018-08-21 12:44:45",
    "vests": 404901.66
  },
  {
    "delegator": "plokmi",
    "sp": 201.40141003898358,
    "time": "2018-09-04 14:43:00",
    "vests": 404595.48
  },
  {
    "delegator": "acdevan",
    "sp": 201.11704559304644,
    "time": "2018-10-01 10:21:27",
    "vests": 404024.22
  },
  {
    "delegator": "kyunga",
    "sp": 201.04994920319265,
    "time": "2018-10-07 15:05:54",
    "vests": 403889.43
  },
  {
    "delegator": "strosalia",
    "sp": 201.0102359456622,
    "time": "2018-10-11 07:06:33",
    "vests": 403809.65
  },
  {
    "delegator": "ogochukwu",
    "sp": 200.9963377988804,
    "time": "2018-10-12 13:54:15",
    "vests": 403781.73
  },
  {
    "delegator": "lcc3108",
    "sp": 200.897477771987,
    "time": "2018-10-21 16:57:24",
    "vests": 403583.13
  },
  {
    "delegator": "thethreehugs",
    "sp": 200.78847289439832,
    "time": "2018-10-31 19:25:48",
    "vests": 403364.15
  },
  {
    "delegator": "resiliencia",
    "sp": 200.6829176642737,
    "time": "2018-11-10 14:33:27",
    "vests": 403152.1
  },
  {
    "delegator": "pialejoana",
    "sp": 200.58138453393414,
    "time": "2018-11-19 22:41:15",
    "vests": 402948.13
  },
  {
    "delegator": "dalz",
    "sp": 200.38131991455487,
    "time": "2018-12-07 19:55:03",
    "vests": 402546.22
  },
  {
    "delegator": "enolife",
    "sp": 160.00368417614564,
    "time": "2019-01-10 16:13:57",
    "vests": 321431.55
  },
  {
    "delegator": "maxwell95",
    "sp": 151.75806601260598,
    "time": "2018-06-08 09:40:24",
    "vests": 304866.92
  },
  {
    "delegator": "drigweeu",
    "sp": 151.72314144318585,
    "time": "2018-06-12 19:33:42",
    "vests": 304796.76
  },
  {
    "delegator": "stans",
    "sp": 151.1646370475472,
    "time": "2018-08-21 14:53:09",
    "vests": 303674.78
  },
  {
    "delegator": "dinsha",
    "sp": 151.09791897400981,
    "time": "2018-08-29 19:22:27",
    "vests": 303540.75
  },
  {
    "delegator": "simplymike",
    "sp": 150.5212305059521,
    "time": "2018-11-09 11:42:15",
    "vests": 302382.24
  },
  {
    "delegator": "for91days",
    "sp": 146.29257996789724,
    "time": "2018-07-31 08:28:24",
    "vests": 293887.3
  },
  {
    "delegator": "ted7",
    "sp": 141.68607605313565,
    "time": "2018-06-02 07:11:18",
    "vests": 284633.29
  },
  {
    "delegator": "rehan12",
    "sp": 120.65411804973358,
    "time": "2018-10-03 22:00:51",
    "vests": 242382.17
  },
  {
    "delegator": "valth",
    "sp": 111.38733454697122,
    "time": "2018-05-22 12:27:57",
    "vests": 223766.12
  },
  {
    "delegator": "monkeydoo",
    "sp": 106.26537962894761,
    "time": "2018-06-02 03:38:24",
    "vests": 213476.62
  },
  {
    "delegator": "chungjh",
    "sp": 105.37692367124443,
    "time": "2018-11-07 08:32:42",
    "vests": 211691.8
  },
  {
    "delegator": "themonetaryfew",
    "sp": 103.0119439312105,
    "time": "2018-09-04 00:24:09",
    "vests": 206940.79
  },
  {
    "delegator": "soosoo",
    "sp": 101.44127414240265,
    "time": "2018-04-18 07:27:21",
    "vests": 203785.47
  },
  {
    "delegator": "leesongyi",
    "sp": 101.4407116457743,
    "time": "2018-04-18 10:01:18",
    "vests": 203784.34
  },
  {
    "delegator": "jisung",
    "sp": 101.26256448351546,
    "time": "2018-05-22 06:17:57",
    "vests": 203426.46
  },
  {
    "delegator": "smartbear",
    "sp": 101.26232554689457,
    "time": "2018-05-22 07:24:06",
    "vests": 203425.98
  },
  {
    "delegator": "mellissaying",
    "sp": 101.26079237024385,
    "time": "2018-05-22 14:22:57",
    "vests": 203422.9
  },
  {
    "delegator": "kr-ebook",
    "sp": 101.25763143786334,
    "time": "2018-05-23 04:45:24",
    "vests": 203416.55
  },
  {
    "delegator": "wony",
    "sp": 101.2575717037081,
    "time": "2018-05-23 05:01:45",
    "vests": 203416.43
  },
  {
    "delegator": "dakeshi",
    "sp": 101.25755179232304,
    "time": "2018-05-23 05:07:06",
    "vests": 203416.39
  },
  {
    "delegator": "zaedol",
    "sp": 101.2559887485947,
    "time": "2018-05-23 12:14:48",
    "vests": 203413.25
  },
  {
    "delegator": "deanlogic",
    "sp": 101.25584439105292,
    "time": "2018-05-23 12:53:57",
    "vests": 203412.96
  },
  {
    "delegator": "johnrenald",
    "sp": 101.25221056327689,
    "time": "2018-05-24 05:27:06",
    "vests": 203405.66
  },
  {
    "delegator": "gidung",
    "sp": 101.25214087342911,
    "time": "2018-05-24 05:45:18",
    "vests": 203405.52
  },
  {
    "delegator": "room9",
    "sp": 101.2513543737187,
    "time": "2018-05-24 09:24:12",
    "vests": 203403.94
  },
  {
    "delegator": "wefund",
    "sp": 101.25082672201422,
    "time": "2018-05-24 12:45:24",
    "vests": 203402.88
  },
  {
    "delegator": "matildah",
    "sp": 101.25019453553811,
    "time": "2018-05-24 14:55:06",
    "vests": 203401.61
  },
  {
    "delegator": "hanen",
    "sp": 101.2455750942009,
    "time": "2018-05-25 11:56:03",
    "vests": 203392.33
  },
  {
    "delegator": "direwolf",
    "sp": 101.23339928222804,
    "time": "2018-05-27 19:33:42",
    "vests": 203367.87
  },
  {
    "delegator": "yann03",
    "sp": 101.2091422373614,
    "time": "2018-06-01 09:24:33",
    "vests": 203319.14
  },
  {
    "delegator": "kuberaleez",
    "sp": 101.19919152267056,
    "time": "2018-06-03 06:31:00",
    "vests": 203299.15
  },
  {
    "delegator": "ab7b13",
    "sp": 101.19319819576323,
    "time": "2018-06-04 09:42:48",
    "vests": 203287.11
  },
  {
    "delegator": "seraphim502",
    "sp": 101.192396762514,
    "time": "2018-06-04 13:21:27",
    "vests": 203285.5
  },
  {
    "delegator": "team101",
    "sp": 101.16401806093698,
    "time": "2018-06-09 22:03:03",
    "vests": 203228.49
  },
  {
    "delegator": "nowoojun",
    "sp": 101.07816016849706,
    "time": "2018-06-26 01:49:00",
    "vests": 203056.01
  },
  {
    "delegator": "transcript-junky",
    "sp": 101.03516153242934,
    "time": "2018-07-04 10:23:57",
    "vests": 202969.63
  },
  {
    "delegator": "didic",
    "sp": 101.02224402136244,
    "time": "2018-07-06 20:35:24",
    "vests": 202943.68
  },
  {
    "delegator": "zoltarian",
    "sp": 101.01233312944177,
    "time": "2018-07-08 17:11:54",
    "vests": 202923.77
  },
  {
    "delegator": "chappuller",
    "sp": 101.0122186389776,
    "time": "2018-07-08 17:42:21",
    "vests": 202923.54
  },
  {
    "delegator": "elementm",
    "sp": 100.78063429702588,
    "time": "2018-08-20 20:18:18",
    "vests": 202458.31
  },
  {
    "delegator": "sambasambo",
    "sp": 100.77343135347529,
    "time": "2018-08-22 04:06:36",
    "vests": 202443.84
  },
  {
    "delegator": "humptydumpty1",
    "sp": 100.74571470545202,
    "time": "2018-08-27 06:24:54",
    "vests": 202388.16
  },
  {
    "delegator": "mermaidvampire",
    "sp": 100.74511238605352,
    "time": "2018-08-27 09:04:33",
    "vests": 202386.95
  },
  {
    "delegator": "otom",
    "sp": 100.68248112430264,
    "time": "2018-09-08 00:09:45",
    "vests": 202261.13
  },
  {
    "delegator": "kenmelendez",
    "sp": 100.65001561093915,
    "time": "2018-09-13 23:41:06",
    "vests": 202195.91
  },
  {
    "delegator": "mers",
    "sp": 100.64128446858412,
    "time": "2018-09-15 14:01:00",
    "vests": 202178.37
  },
  {
    "delegator": "aurorax",
    "sp": 100.63758592880659,
    "time": "2018-09-16 06:16:54",
    "vests": 202170.94
  },
  {
    "delegator": "gremayo",
    "sp": 100.6283719353635,
    "time": "2018-09-18 11:46:48",
    "vests": 202152.43
  },
  {
    "delegator": "jibupune",
    "sp": 100.62776961596501,
    "time": "2018-09-18 14:28:15",
    "vests": 202151.22
  },
  {
    "delegator": "cryptouru",
    "sp": 100.6271224959501,
    "time": "2018-09-18 17:21:51",
    "vests": 202149.92
  },
  {
    "delegator": "bobby.madagascar",
    "sp": 100.59539868168063,
    "time": "2018-09-24 13:58:48",
    "vests": 202086.19
  },
  {
    "delegator": "ecoinstant",
    "sp": 100.5305273891089,
    "time": "2018-10-06 14:33:21",
    "vests": 201955.87
  },
  {
    "delegator": "preparedwombat",
    "sp": 100.51935710208227,
    "time": "2018-10-08 15:56:51",
    "vests": 201933.43
  },
  {
    "delegator": "jeronimorubio",
    "sp": 100.51360271179584,
    "time": "2018-10-09 17:25:54",
    "vests": 201921.87
  },
  {
    "delegator": "parisfoodhunter",
    "sp": 100.38873841599555,
    "time": "2018-11-01 19:58:36",
    "vests": 201671.03
  },
  {
    "delegator": "suddenly12",
    "sp": 100.37158973560038,
    "time": "2018-11-05 00:17:45",
    "vests": 201636.58
  },
  {
    "delegator": "chesatochi",
    "sp": 100.36035473657229,
    "time": "2018-11-07 13:03:42",
    "vests": 201614.01
  },
  {
    "delegator": "normalbro",
    "sp": 100.30061560350343,
    "time": "2018-11-18 03:12:24",
    "vests": 201494
  },
  {
    "delegator": "jccr",
    "sp": 100.29312892271551,
    "time": "2018-11-19 12:00:51",
    "vests": 201478.96
  },
  {
    "delegator": "lobinia",
    "sp": 100.2917401036066,
    "time": "2018-11-19 18:04:39",
    "vests": 201476.17
  },
  {
    "delegator": "dwiitavita",
    "sp": 100.28944033863053,
    "time": "2018-11-20 04:09:48",
    "vests": 201471.55
  },
  {
    "delegator": "newtechblog",
    "sp": 100.28502498899033,
    "time": "2018-11-20 23:28:24",
    "vests": 201462.68
  },
  {
    "delegator": "hamismsf",
    "sp": 100.281719699068,
    "time": "2018-11-21 13:46:39",
    "vests": 201456.04
  },
  {
    "delegator": "replayphoto",
    "sp": 100.2270231242692,
    "time": "2018-12-01 08:01:00",
    "vests": 201346.16
  },
  {
    "delegator": "bluemist",
    "sp": 100.21364267349932,
    "time": "2018-12-03 17:20:27",
    "vests": 201319.28
  },
  {
    "delegator": "mcoinz79",
    "sp": 100.20555367331293,
    "time": "2018-12-05 04:01:27",
    "vests": 201303.03
  },
  {
    "delegator": "kriptonik",
    "sp": 100.03107518375403,
    "time": "2019-01-05 12:18:30",
    "vests": 200952.52
  },
  {
    "delegator": "mamun123456",
    "sp": 100.01951164687219,
    "time": "2019-01-07 14:03:57",
    "vests": 200929.29
  },
  {
    "delegator": "yonghwanny",
    "sp": 96.82158391287564,
    "time": "2018-06-12 10:12:12",
    "vests": 194504.97
  },
  {
    "delegator": "dray91eu",
    "sp": 91.80017651163047,
    "time": "2018-08-13 21:54:12",
    "vests": 184417.46
  },
  {
    "delegator": "mobi72",
    "sp": 85.23730434563501,
    "time": "2018-11-22 00:41:18",
    "vests": 171233.3
  },
  {
    "delegator": "anikearn",
    "sp": 80.27317702140202,
    "time": "2018-11-10 14:30:33",
    "vests": 161260.86
  },
  {
    "delegator": "chrisli",
    "sp": 75.62092172158619,
    "time": "2018-08-12 03:42:57",
    "vests": 151914.94
  },
  {
    "delegator": "sbd.giveaway",
    "sp": 70.51407456698763,
    "time": "2018-08-29 08:30:27",
    "vests": 141655.79
  },
  {
    "delegator": "wilhb81",
    "sp": 65.72450040000759,
    "time": "2018-06-19 05:19:42",
    "vests": 132034.01
  },
  {
    "delegator": "daan007",
    "sp": 60.607304303016704,
    "time": "2018-07-08 17:54:27",
    "vests": 121754.07
  },
  {
    "delegator": "artcreator",
    "sp": 60.46853190474209,
    "time": "2018-08-20 19:11:06",
    "vests": 121475.29
  },
  {
    "delegator": "hafizullah",
    "sp": 52.186640175443515,
    "time": "2018-12-12 04:41:57",
    "vests": 104837.79
  },
  {
    "delegator": "team2dev",
    "sp": 50.54529990316109,
    "time": "2018-06-23 17:53:09",
    "vests": 101540.5
  },
  {
    "delegator": "hungryhustle",
    "sp": 50.44038183735887,
    "time": "2018-08-02 08:12:27",
    "vests": 101329.73
  },
  {
    "delegator": "just2random",
    "sp": 50.434672247688844,
    "time": "2018-08-04 11:15:00",
    "vests": 101318.26
  },
  {
    "delegator": "freyman",
    "sp": 50.42810149061437,
    "time": "2018-08-06 21:49:21",
    "vests": 101305.06
  },
  {
    "delegator": "mr-chuckles",
    "sp": 50.40739862798346,
    "time": "2018-08-14 13:44:36",
    "vests": 101263.47
  },
  {
    "delegator": "hattaarshavin",
    "sp": 50.386825189355555,
    "time": "2018-08-22 03:08:18",
    "vests": 101222.14
  },
  {
    "delegator": "ericwilson",
    "sp": 50.373509450587186,
    "time": "2018-08-27 00:39:39",
    "vests": 101195.39
  },
  {
    "delegator": "itsravi",
    "sp": 50.29155916746806,
    "time": "2018-09-26 20:48:27",
    "vests": 101030.76
  },
  {
    "delegator": "moneyhacks",
    "sp": 50.21178420316829,
    "time": "2018-10-26 08:40:00",
    "vests": 100870.5
  },
  {
    "delegator": "bjornb",
    "sp": 50.19837886316709,
    "time": "2018-10-31 08:07:12",
    "vests": 100843.57
  },
  {
    "delegator": "lemmybe",
    "sp": 50.16831764955131,
    "time": "2018-11-11 12:00:27",
    "vests": 100783.18
  },
  {
    "delegator": "timmyeu",
    "sp": 50.15995486782016,
    "time": "2018-11-14 14:18:24",
    "vests": 100766.38
  },
  {
    "delegator": "elihs",
    "sp": 50.12600097842239,
    "time": "2018-11-26 20:48:54",
    "vests": 100698.17
  },
  {
    "delegator": "gabbynhice",
    "sp": 50.006766626751826,
    "time": "2019-01-08 15:51:45",
    "vests": 100458.64
  },
  {
    "delegator": "dumnebari",
    "sp": 40.14894850298582,
    "time": "2018-11-04 20:48:39",
    "vests": 80655.26
  },
  {
    "delegator": "paradigmprospect",
    "sp": 38.074067687790375,
    "time": "2018-12-07 01:41:45",
    "vests": 76487.03
  },
  {
    "delegator": "randomgoodstuff",
    "sp": 30.290771974288482,
    "time": "2018-07-16 18:22:30",
    "vests": 60851.16
  },
  {
    "delegator": "lpessin",
    "sp": 30.218647959703475,
    "time": "2018-08-30 09:15:18",
    "vests": 60706.27
  },
  {
    "delegator": "shookriya",
    "sp": 30.10279356564926,
    "time": "2018-11-10 09:18:36",
    "vests": 60473.53
  },
  {
    "delegator": "steeemlover",
    "sp": 30.051088676457844,
    "time": "2018-12-11 11:28:48",
    "vests": 60369.66
  },
  {
    "delegator": "nataharuka",
    "sp": 27.119485673521215,
    "time": "2018-10-22 20:28:33",
    "vests": 54480.36
  },
  {
    "delegator": "enjar",
    "sp": 25.031687347258885,
    "time": "2018-12-19 07:28:39",
    "vests": 50286.18
  },
  {
    "delegator": "rangertx",
    "sp": 20.248529624118998,
    "time": "2018-05-26 01:22:15",
    "vests": 40677.29
  },
  {
    "delegator": "lusterdoom",
    "sp": 20.245279090505637,
    "time": "2018-05-29 03:08:24",
    "vests": 40670.76
  },
  {
    "delegator": "onlyforyou",
    "sp": 20.080333176550997,
    "time": "2018-10-30 10:18:00",
    "vests": 40339.4
  },
  {
    "delegator": "xomegax",
    "sp": 20.033023725614704,
    "time": "2018-12-12 09:45:06",
    "vests": 40244.36
  },
  {
    "delegator": "tim3w4rp",
    "sp": 15.188429423828385,
    "time": "2018-05-23 11:14:42",
    "vests": 30512.05
  },
  {
    "delegator": "schroders",
    "sp": 15.188329866903015,
    "time": "2018-05-23 14:23:54",
    "vests": 30511.85
  },
  {
    "delegator": "earlmonk",
    "sp": 11.068271045196557,
    "time": "2018-09-19 22:00:21",
    "vests": 22235.06
  },
  {
    "delegator": "ederaleng",
    "sp": 11.02293779922888,
    "time": "2018-12-04 15:22:03",
    "vests": 22143.99
  },
  {
    "delegator": "unicron",
    "sp": 10.125830344710959,
    "time": "2018-05-23 01:39:12",
    "vests": 20341.79
  },
  {
    "delegator": "amala",
    "sp": 10.07748550175081,
    "time": "2018-08-21 21:52:54",
    "vests": 20244.67
  },
  {
    "delegator": "fruitdaddy",
    "sp": 10.07745065682693,
    "time": "2018-08-21 23:24:00",
    "vests": 20244.6
  },
  {
    "delegator": "vegan4theanimals",
    "sp": 10.07745065682693,
    "time": "2018-08-21 23:25:57",
    "vests": 20244.6
  },
  {
    "delegator": "birdbanter",
    "sp": 10.0719949373166,
    "time": "2018-09-01 00:50:45",
    "vests": 20233.64
  },
  {
    "delegator": "everydaycoach",
    "sp": 10.061207944452656,
    "time": "2018-09-21 11:57:15",
    "vests": 20211.97
  },
  {
    "delegator": "okekemmichael",
    "sp": 5.062121205875645,
    "time": "2018-05-26 02:17:21",
    "vests": 10169.3
  },
  {
    "delegator": "streetsmart",
    "sp": 5.059278855656304,
    "time": "2018-06-05 20:07:42",
    "vests": 10163.59
  },
  {
    "delegator": "doodleman",
    "sp": 5.033662858758349,
    "time": "2018-08-07 03:58:18",
    "vests": 10112.13
  },
  {
    "delegator": "walterben",
    "sp": 4.960085313062926,
    "time": "2018-08-03 04:19:00",
    "vests": 9964.32
  },
  {
    "delegator": "steeming-ali",
    "sp": 4.041702543593227,
    "time": "2018-07-02 16:44:39",
    "vests": 8119.38
  },
  {
    "delegator": "anutta",
    "sp": 2.0892020789100614,
    "time": "2018-08-20 17:24:15",
    "vests": 4197
  },
  {
    "delegator": "hensey",
    "sp": 2.01588835906687,
    "time": "2018-08-18 07:41:00",
    "vests": 4049.72
  },
  {
    "delegator": "fashionsteemit",
    "sp": 1.5152912490702288,
    "time": "2018-07-07 09:58:45",
    "vests": 3044.07
  },
  {
    "delegator": "ciontheemrald",
    "sp": 1.004001725288744,
    "time": "2018-10-30 17:01:12",
    "vests": 2016.94
  }
]